ksvian/__init__.py
ksvian/core.py
mylibrary/__init__.py
mylibrary/core.py
ksvian-0.1.1.dist-info/LICENSE
ksvian-0.1.1.dist-info/METADATA
ksvian-0.1.1.dist-info/WHEEL
ksvian-0.1.1.dist-info/top_level.txt
ksvian-0.1.1.dist-info/RECORD
