Metadata-Version: 2.1
Name: ksvian
Version: 0.1.1
Summary: A custom library with various functions and models for ANN labouratory
Home-page: https://github.com/prashanthktgowda/ksvian
Author: prashanthktgowda
Author-email: prashanthktgowda123@gmail.com
License: MIT
Platform: UNKNOWN
Classifier: Programming Language :: Python :: 3
Classifier: License :: OSI Approved :: MIT License
Classifier: Operating System :: OS Independent
Requires-Python: >=3.6
Requires-Dist: numpy
Requires-Dist: scikit-learn
